<?xml version="1.0" encoding="ISO-8859-9"?>
<Report>
<title>Implemented Data List</title>
<modelname>N8I_ORT_YYY_0112_TEMPLATE</modelname>
<subset>(complete model)</subset>
<datetime>03 Jul. 2023  11:31</datetime>
<THLENT NAME="CHILD" IMPLMNTB="TRECDATA:VDVYYYC">
<TRELMM NAME="ALWAYS_HAS_ONE" DENTY="PARENT" />
<TATTRUSR  NAME="CINSTANCE_ID">
<IMPLNTBY DFIELD="CINSTANCE_ID" ROLEFLD="P" TRECDATA="VDVYYYC" />
</TATTRUSR>
<TATTRUSR  NAME="CREFERENCE_ID">
<IMPLNTBY DFIELD="CREFERENCE_ID" ROLEFLD="P" TRECDATA="VDVYYYC" />
</TATTRUSR>
<TATTRUSR  NAME="CCREATE_USER_ID">
<IMPLNTBY DFIELD="CCREATE_USERID" ROLEFLD="P" TRECDATA="VDVYYYC" />
</TATTRUSR>
<TATTRUSR  NAME="CUPDATE_USER_ID">
<IMPLNTBY DFIELD="CUPDATE_USERID" ROLEFLD="P" TRECDATA="VDVYYYC" />
</TATTRUSR>
<TATTRUSR  NAME="CPARENT_PKEY_ATTR_TEXT">
<IMPLNTBY DFIELD="CPARENT_PKEY_ATTR" ROLEFLD="P" TRECDATA="VDVYYYC" />
</TATTRUSR>
<TATTRUSR  NAME="CKEY_ATTR_NUM">
<IMPLNTBY DFIELD="CKEY_ATTR" ROLEFLD="P" TRECDATA="VDVYYYC" />
</TATTRUSR>
<TATTRUSR  NAME="CSEARCH_ATTR_TEXT">
<IMPLNTBY DFIELD="CSEARCH_ATTR" ROLEFLD="P" TRECDATA="VDVYYYC" />
</TATTRUSR>
<TATTRUSR  NAME="COTHER_ATTR_TEXT">
<IMPLNTBY DFIELD="COTHER_ATTR" ROLEFLD="P" TRECDATA="VDVYYYC" />
</TATTRUSR>
</THLENT>
<THLENT NAME="PARENT" IMPLMNTB="TRECDATA:VDVYYYP">
<TRELMM NAME="SOMETIMES_HAS_ONE_OR_MORE" DENTY="CHILD" />
<TRELMM NAME="ALWAYS_HAS_ONE" DENTY="TYPE" />
<TATTRUSR  NAME="PINSTANCE_ID">
<IMPLNTBY DFIELD="PINSTANCE_ID" ROLEFLD="P" TRECDATA="VDVYYYP" />
</TATTRUSR>
<TATTRUSR  NAME="PREFERENCE_ID">
<IMPLNTBY DFIELD="PREFERENCE_ID" ROLEFLD="P" TRECDATA="VDVYYYP" />
</TATTRUSR>
<TATTRUSR  NAME="PCREATE_USER_ID">
<IMPLNTBY DFIELD="PCREATE_USERID" ROLEFLD="P" TRECDATA="VDVYYYP" />
</TATTRUSR>
<TATTRUSR  NAME="PUPDATE_USER_ID">
<IMPLNTBY DFIELD="PUPDATE_USERID" ROLEFLD="P" TRECDATA="VDVYYYP" />
</TATTRUSR>
<TATTRUSR  NAME="PKEY_ATTR_TEXT">
<IMPLNTBY DFIELD="PKEY_ATTR" ROLEFLD="P" TRECDATA="VDVYYYP" />
</TATTRUSR>
<TATTRUSR  NAME="PSEARCH_ATTR_TEXT">
<IMPLNTBY DFIELD="PSEARCH_ATTR" ROLEFLD="P" TRECDATA="VDVYYYP" />
</TATTRUSR>
<TATTRUSR  NAME="POTHER_ATTR_TEXT">
<IMPLNTBY DFIELD="POTHER_ATTR" ROLEFLD="P" TRECDATA="VDVYYYP" />
</TATTRUSR>
<TATTRUSR  NAME="PTYPE_TKEY_ATTR_TEXT">
<IMPLNTBY DFIELD="PTYPE_TKEY_ATTR_TE" ROLEFLD="P" TRECDATA="VDVYYYP" />
</TATTRUSR>
</THLENT>
<THLENT NAME="TYPE" IMPLMNTB="TRECDATA:VDVYYYT">
<TRELMM NAME="SOMETIMES_HAS_ONE_OR_MORE" DENTY="PARENT" />
<TATTRUSR  NAME="TINSTANCE_ID">
<IMPLNTBY DFIELD="TINSTANCE_ID" ROLEFLD="P" TRECDATA="VDVYYYT" />
</TATTRUSR>
<TATTRUSR  NAME="TREFERENCE_ID">
<IMPLNTBY DFIELD="TREFERENCE_ID" ROLEFLD="P" TRECDATA="VDVYYYT" />
</TATTRUSR>
<TATTRUSR  NAME="TCREATE_USER_ID">
<IMPLNTBY DFIELD="TCREATE_USERID" ROLEFLD="P" TRECDATA="VDVYYYT" />
</TATTRUSR>
<TATTRUSR  NAME="TUPDATE_USER_ID">
<IMPLNTBY DFIELD="TUPDATE_USERID" ROLEFLD="P" TRECDATA="VDVYYYT" />
</TATTRUSR>
<TATTRUSR  NAME="TKEY_ATTR_TEXT">
<IMPLNTBY DFIELD="TKEY_ATTR" ROLEFLD="P" TRECDATA="VDVYYYT" />
</TATTRUSR>
<TATTRUSR  NAME="TSEARCH_ATTR_TEXT">
<IMPLNTBY DFIELD="TSEARCH_ATTR" ROLEFLD="P" TRECDATA="VDVYYYT" />
</TATTRUSR>
<TATTRUSR  NAME="TOTHER_ATTR_TEXT">
<IMPLNTBY DFIELD="TOTHER_ATTR" ROLEFLD="P" TRECDATA="VDVYYYT" />
</TATTRUSR>
<TATTRUSR  NAME="TOTHER_ATTR_DATE">
<IMPLNTBY DFIELD="TOTHER_DATE" ROLEFLD="P" TRECDATA="VDVYYYT" />
</TATTRUSR>
<TATTRUSR  NAME="TOTHER_ATTR_TIME">
<IMPLNTBY DFIELD="TOTHER_TIME" ROLEFLD="P" TRECDATA="VDVYYYT" />
</TATTRUSR>
<TATTRUSR  NAME="TOTHER_ATTR_AMOUNT">
<IMPLNTBY DFIELD="TOTHER_AMOUNT" ROLEFLD="P" TRECDATA="VDVYYYT" />
</TATTRUSR>
</THLENT>
</Report>
